richertext/__init__.py
richertext/_version.py
richertext/api.py
richertext/exceptions.py
richertext/cli/__init__.py
richertext/cli/main.py
richertext/enrichments/__init__.py
richertext/enrichments/classifier.py
richertext/enrichments/interface.py
richertext/enrichments/labeler.py
richertext/enrichments/reasoner.py
richertext/enrichments/scorer.py
richertext/enrichments/summarizer.py
richertext/pipeline/__init__.py
richertext/pipeline/runner.py
richertext/providers/__init__.py
richertext/providers/gemini.py
richertext/providers/interface.py
richertext/utils/__init__.py
richertext/utils/config.py
richertext/utils/rate_limit.py
richertext-0.1.0.dist-info/licenses/LICENSE
richertext-0.1.0.dist-info/METADATA
richertext-0.1.0.dist-info/WHEEL
richertext-0.1.0.dist-info/entry_points.txt
richertext-0.1.0.dist-info/top_level.txt
richertext-0.1.0.dist-info/RECORD
