Metadata-Version: 2.4
Name: richertext
Version: 0.1.0
Summary: LLM-powered CSV enrichment made easy
Author: RicherText Contributors
License-Expression: MIT
Project-URL: Homepage, https://github.com/uniquehash/RicherText
Project-URL: Documentation, https://github.com/uniquehash/RicherText#readme
Project-URL: Repository, https://github.com/uniquehash/RicherText
Project-URL: Issues, https://github.com/uniquehash/RicherText/issues
Keywords: llm,csv,enrichment,classification,summarization,nlp
Classifier: Development Status :: 3 - Alpha
Classifier: Intended Audience :: Developers
Classifier: Programming Language :: Python :: 3
Classifier: Programming Language :: Python :: 3.9
Classifier: Programming Language :: Python :: 3.10
Classifier: Programming Language :: Python :: 3.11
Classifier: Programming Language :: Python :: 3.12
Classifier: Topic :: Scientific/Engineering :: Artificial Intelligence
Classifier: Topic :: Text Processing
Requires-Python: >=3.9
License-File: LICENSE
Requires-Dist: google-genai>=0.3.0
Requires-Dist: pyyaml>=6.0
Requires-Dist: python-dotenv>=1.0.0
Provides-Extra: dev
Requires-Dist: pytest>=7.0.0; extra == "dev"
Requires-Dist: pytest-cov>=4.0.0; extra == "dev"
Requires-Dist: black>=23.0.0; extra == "dev"
Requires-Dist: ruff>=0.1.0; extra == "dev"
Dynamic: license-file
